modules/__init__.py
modules/hook.py
modules/ALFA/ALFA.py
modules/ALFA/__init__.py
modules/tin_score/__init__.py
modules/tin_score/tin_score.py
modules/zpca/__init__.py
modules/zpca/zpca.py
multiqc_plugins-1.3.dist-info/LICENSE
multiqc_plugins-1.3.dist-info/METADATA
multiqc_plugins-1.3.dist-info/WHEEL
multiqc_plugins-1.3.dist-info/entry_points.txt
multiqc_plugins-1.3.dist-info/top_level.txt
multiqc_plugins-1.3.dist-info/RECORD
